create_django_project.py
automate_django_project-0.0.1.dist-info/LICENSE.txt
automate_django_project-0.0.1.dist-info/METADATA
automate_django_project-0.0.1.dist-info/WHEEL
automate_django_project-0.0.1.dist-info/top_level.txt
automate_django_project-0.0.1.dist-info/RECORD
